remosh.py
setup.cfg
setup.py
remosh.egg-info/PKG-INFO
remosh.egg-info/SOURCES.txt
remosh.egg-info/dependency_links.txt
remosh.egg-info/entry_points.txt
remosh.egg-info/requires.txt
remosh.egg-info/top_level.txt